[
  {
    "year":    {
      "type": "zbs", "data": [
        {"chartName": "НПВ", "typeOfData": " ", "data": [{"pv": 75, "npv": 25}]},
        {
          "chartName": "Скорость строительства скважин", "typeOfData": " ", "data": [
          {
            "period": "2013", "data": [
            {"type": "ННС", "plan": 27, "fact": 23},
            {"type": "ГС", "plan": 23, "fact": 23}
          ]
          },
          {
            "period": "2014", "data": [
            {"type": "ННС", "plan": 29, "fact": 23},
            {"type": "ГС", "plan": 39, "fact": 23}
          ]
          },
          {
            "period": "2015", "data": [
            {"type": "ННС", "plan": 29, "fact": 23},
            {"type": "ГС", "plan": 28, "fact": 23}
          ]
          }
        ]
        },
        {
          "chartName": "Количество бригад бурения", "typeOfData": " ", "data": [
          {"period": "2013", "plan": 20, "fact": 19},
          {"period": "2014", "plan": 23, "fact": 20},
          {"period": "2015", "plan": 19, "fact": 24}
        ]
        },
        {
          "chartName": "Количество бригад освоения", "typeOfData": " ", "data": [
          {"period": "2013", "plan": 20, "fact": 19},
          {"period": "2014", "plan": 23, "fact": 20},
          {"period": "2015", "plan": 19, "fact": 24}
        ]
        },
        {
          "chartName": "Количество введенных скважин", "typeOfData": " ", "data": [
          {"period": "2013", "plan": 20, "fact": 19},
          {"period": "2014", "plan": 23, "fact": 20},
          {"period": "2015", "plan": 19, "fact": 24}
        ]
        },
        {
          "chartName": "Количество скважин законченных строительством", "typeOfData": " ", "data": [
          {"period": "2013", "plan": 20, "fact": 19},
          {"period": "2014", "plan": 23, "fact": 20},
          {"period": "2015", "plan": 19, "fact": 24}
        ]
        },
        {
          "chartName": "Количество скважин законченных бурением", "typeOfData": " ", "data": [
          {"period": "2013", "plan": 20, "fact": 19},
          {"period": "2014", "plan": 23, "fact": 20},
          {"period": "2015", "plan": 19, "fact": 24}
        ]
        },
        {
          "chartName": "Коэффициент аварийности", "typeOfData": " ", "data": [
          {"period": "2013", "LastYear": 20, "thisYear": 19},
          {"period": "2014", "LastYear": 23, "thisYear": 20},
          {"period": "2015", "LastYear": 19, "thisYear": 24},
          {"period": "2016", "LastYear": 19, "thisYear": 24},
          {"period": "2017", "LastYear": 19, "thisYear": 24}
        ]
        },
        {
          "chartName": "Продолжительность строительства скважин", "typeOfData": " ", "data": [
          {
            "period": "2013", "data": [
            {"type": "ННС", "plan": 21, "fact": 23},
            {"type": "ГС", "plan": 22, "fact": 23}
          ]
          },
          {
            "period": "2014", "data": [
            {"type": "ННС", "plan": 24, "fact": 23},
            {"type": "ГС", "plan": 19, "fact": 23}
          ]
          },
          {
            "period": "2015", "data": [
            {"type": "ННС", "plan": 19, "fact": 23},
            {"type": "ГС", "plan": 18, "fact": 23}
          ]
          }
        ]
        },
        {
          "chartName": "Продолжительность бурения скважин", "typeOfData": " ", "data": [
          {
            "period": "2013", "data": [
            {"type": "ННС", "plan": 21, "fact": 23},
            {"type": "ГС", "plan": 22, "fact": 23}
          ]
          },
          {
            "period": "2014", "data": [
            {"type": "ННС", "plan": 24, "fact": 23},
            {"type": "ГС", "plan": 19, "fact": 23}
          ]
          },
          {
            "period": "2015", "data": [
            {"type": "ННС", "plan": 19, "fact": 23},
            {"type": "ГС", "plan": 18, "fact": 23}
          ]
          }
        ]
        },
        {
          "chartName": "Продолжительность освоения скважин", "typeOfData": " ", "data": [
          {
            "period": "2013", "data": [
            {"type": "ННС", "plan": 21, "fact": 23},
            {"type": "ГС", "plan": 22, "fact": 23}
          ]
          },
          {
            "period": "2014", "data": [
            {"type": "ННС", "plan": 24, "fact": 23},
            {"type": "ГС", "plan": 19, "fact": 23}
          ]
          },
          {
            "period": "2015", "data": [
            {"type": "ННС", "plan": 19, "fact": 23},
            {"type": "ГС", "plan": 18, "fact": 23}
          ]
          }
        ]
        },
        {
          "chartName": "Коэффициент тяжести аварий", "typeOfData": " ", "data": [
          {"period": "2013", "LastYear": 20, "thisYear": 19},
          {"period": "2014", "LastYear": 23, "thisYear": 20},
          {"period": "2015", "LastYear": 19, "thisYear": 24},
          {"period": "2016", "LastYear": 19, "thisYear": 24},
          {"period": "2017", "LastYear": 19, "thisYear": 24}
        ]
        }
      ]
    },
    "quarter": {
      "type": "zbs", "data": [
        {"chartName": "НПВ", "typeOfData": "%", "data": [{"pv": 70, "npv": 30}]},
        {
          "chartName": "Скорость строительства скважин", "typeOfData": " ", "data": [
          {
            "period": "1-ый квартал", "data": [
            {"type": "ННС", "plan": 21, "fact": 23},
            {"type": "ГС", "plan": 22, "fact": 23}
          ]
          },
          {
            "period": "2-ой квартал", "data": [
            {"type": "ННС", "plan": 24, "fact": 23},
            {"type": "ГС", "plan": 19, "fact": 23}
          ]
          },
          {
            "period": "3-ий квартал", "data": [
            {"type": "ННС", "plan": 19, "fact": 23},
            {"type": "ГС", "plan": 18, "fact": 23}
          ]
          }
        ]
        },
        {
          "chartName": "Количество бригад бурения", "typeOfData": " ", "data": [
          {"period": "1-ый квартал", "plan": 20, "fact": 19},
          {"period": "2-ой квартал", "plan": 23, "fact": 20},
          {"period": "3-ий квартал", "plan": 19, "fact": 24}
        ]
        },
        {
          "chartName": "Количество бригад освоения", "typeOfData": " ", "data": [
          {"period": "1-ый квартал", "plan": 20, "fact": 19},
          {"period": "2-ой квартал", "plan": 23, "fact": 20},
          {"period": "3-ий квартал", "plan": 19, "fact": 24}
        ]
        },
        {
          "chartName": "Количество введенных скважин", "typeOfData": " ", "data": [
          {"period": "1-ый квартал", "plan": 20, "fact": 19},
          {"period": "2-ой квартал", "plan": 23, "fact": 20},
          {"period": "3-ий квартал", "plan": 19, "fact": 24}
        ]
        },
        {
          "chartName": "Количество скважин законченных строительством", "typeOfData": " ", "data": [
          {"period": "1-ый квартал", "plan": 20, "fact": 19},
          {"period": "2-ой квартал", "plan": 23, "fact": 20},
          {"period": "3-ий квартал", "plan": 19, "fact": 24}
        ]
        },
        {
          "chartName": "Количество скважин законченных бурением", "typeOfData": " ", "data": [
          {"period": "1-ый квартал", "plan": 20, "fact": 19},
          {"period": "2-ой квартал", "plan": 23, "fact": 20},
          {"period": "3-ий квартал", "plan": 19, "fact": 24}
        ]
        },
        {
          "chartName": "Коэффициент аварийности", "typeOfData": " ", "data": [
          {"period": "1-ый квартал", "LastYear": 20, "thisYear": 19},
          {"period": "2-ой квартал", "LastYear": 23, "thisYear": 20},
          {"period": "3-ий квартал", "LastYear": 19, "thisYear": 24},
          {"period": "4-ый квартал", "LastYear": 19, "thisYear": 24},
          {"period": "1-ый квартал", "LastYear": 19, "thisYear": 24}
        ]
        },
        {
          "chartName": "Продолжительность строительства скважин", "typeOfData": " ", "data": [
          {
            "period": "1-ый квартал", "data": [
            {"type": "ННС", "plan": 21, "fact": 23},
            {"type": "ГС", "plan": 22, "fact": 23}
          ]
          },
          {
            "period": "2-ой квартал", "data": [
            {"type": "ННС", "plan": 24, "fact": 23},
            {"type": "ГС", "plan": 19, "fact": 23}
          ]
          },
          {
            "period": "3-ий квартал", "data": [
            {"type": "ННС", "plan": 19, "fact": 23},
            {"type": "ГС", "plan": 18, "fact": 23}
          ]
          }
        ]
        },
        {
          "chartName": "Продолжительность бурения скважин", "typeOfData": " ", "data": [
          {
            "period": "1-ый квартал", "data": [
            {"type": "ННС", "plan": 21, "fact": 23},
            {"type": "ГС", "plan": 22, "fact": 23}
          ]
          },
          {
            "period": "2-ой квартал", "data": [
            {"type": "ННС", "plan": 24, "fact": 23},
            {"type": "ГС", "plan": 19, "fact": 23}
          ]
          },
          {
            "period": "3-ий квартал", "data": [
            {"type": "ННС", "plan": 19, "fact": 23},
            {"type": "ГС", "plan": 18, "fact": 23}
          ]
          }
        ]
        },
        {
          "chartName": "Продолжительность освоения скважин", "typeOfData": " ", "data": [
          {
            "period": "1-ый квартал", "data": [
            {"type": "ННС", "plan": 21, "fact": 23},
            {"type": "ГС", "plan": 22, "fact": 23}
          ]
          },
          {
            "period": "2-ой квартал", "data": [
            {"type": "ННС", "plan": 24, "fact": 23},
            {"type": "ГС", "plan": 19, "fact": 23}
          ]
          },
          {
            "period": "3-ий квартал", "data": [
            {"type": "ННС", "plan": 19, "fact": 23},
            {"type": "ГС", "plan": 18, "fact": 23}
          ]
          }
        ]
        },
        {
          "chartName": "Коэффициент тяжести аварий", "typeOfData": " ", "data": [
          {"period": "1-ый квартал", "LastYear": 20, "thisYear": 19},
          {"period": "2-ой квартал", "LastYear": 23, "thisYear": 20},
          {"period": "3-ий квартал", "LastYear": 19, "thisYear": 24},
          {"period": "4-ый квартал", "LastYear": 19, "thisYear": 24},
          {"period": "1-ый квартал", "LastYear": 19, "thisYear": 24}
        ]
        }
      ]
    },
    "month":   {
      "type": "zbs", "data": [
        {"chartName": "НПВ", "typeOfData": "%", "data": [{"pv": 79, "npv": 21}]},
        {
          "chartName": "Скорость строительства скважин", "typeOfData": " ", "data": [
          {
            "period": "Январь", "data": [
            {"type": "ННС", "plan": 21, "fact": 23},
            {"type": "ГС", "plan": 22, "fact": 23}
          ]
          },
          {
            "period": "Февраль", "data": [
            {"type": "ННС", "plan": 24, "fact": 20},
            {"type": "ГС", "plan": 19, "fact": 21}
          ]
          },
          {
            "period": "Март", "data": [
            {"type": "ННС", "plan": 19, "fact": 23},
            {"type": "ГС", "plan": 18, "fact": 25}
          ]
          }
        ]
        },
        {
          "chartName": "Количество бригад бурения", "typeOfData": " ", "data": [
          {"period": "Январь", "plan": 20, "fact": 19},
          {"period": "Февраль", "plan": 23, "fact": 20},
          {"period": "Март", "plan": 19, "fact": 24}
        ]
        },
        {
          "chartName": "Количество бригад освоения", "typeOfData": " ", "data": [
          {"period": "Январь", "plan": 20, "fact": 19},
          {"period": "Февраль", "plan": 23, "fact": 20},
          {"period": "Март", "plan": 19, "fact": 24}
        ]
        },
        {
          "chartName": "Количество введенных скважин", "typeOfData": " ", "data": [
          {"period": "Январь", "plan": 20, "fact": 19},
          {"period": "Февраль", "plan": 23, "fact": 20},
          {"period": "Март", "plan": 19, "fact": 24}
        ]
        },
        {
          "chartName": "Количество скважин законченных строительством", "typeOfData": " ", "data": [
          {"period": "Январь", "plan": 20, "fact": 19},
          {"period": "Февраль", "plan": 23, "fact": 20},
          {"period": "Март", "plan": 19, "fact": 24}
        ]
        },
        {
          "chartName": "Количество скважин законченных бурением", "typeOfData": " ", "data": [
          {"period": "Январь", "plan": 20, "fact": 19},
          {"period": "Февраль", "plan": 23, "fact": 20},
          {"period": "Март", "plan": 19, "fact": 24}
        ]
        },
        {
          "chartName": "Коэффициент аварийности", "typeOfData": " ", "data": [
          {"period": "Январь", "LastYear": 20, "thisYear": 19},
          {"period": "Февраль", "LastYear": 23, "thisYear": 20},
          {"period": "Март", "LastYear": 19, "thisYear": 24},
          {"period": "Апрель", "LastYear": 19, "thisYear": 24},
          {"period": "Май", "LastYear": 19, "thisYear": 24}
        ]
        },
        {
          "chartName": "Продолжительность строительства скважин", "typeOfData": " ", "data": [
          {
            "period": "Январь", "data": [
            {"type": "ННС", "plan": 21, "fact": 23},
            {"type": "ГС", "plan": 22, "fact": 23}
          ]
          },
          {
            "period": "Февраль", "data": [
            {"type": "ННС", "plan": 24, "fact": 23},
            {"type": "ГС", "plan": 19, "fact": 23}
          ]
          },
          {
            "period": "Март", "data": [
            {"type": "ННС", "plan": 19, "fact": 23},
            {"type": "ГС", "plan": 18, "fact": 23}
          ]
          }
        ]
        },
        {
          "chartName": "Продолжительность бурения скважин", "typeOfData": " ", "data": [
          {
            "period": "Январь", "data": [
            {"type": "ННС", "plan": 21, "fact": 23},
            {"type": "ГС", "plan": 22, "fact": 23}
          ]
          },
          {
            "period": "Февраль", "data": [
            {"type": "ННС", "plan": 24, "fact": 23},
            {"type": "ГС", "plan": 19, "fact": 23}
          ]
          },
          {
            "period": "Март", "data": [
            {"type": "ННС", "plan": 19, "fact": 23},
            {"type": "ГС", "plan": 18, "fact": 23}
          ]
          }
        ]
        },
        {
          "chartName": "Продолжительность освоения скважин", "typeOfData": " ", "data": [
          {
            "period": "Январь", "data": [
            {"type": "ННС", "plan": 21, "fact": 23},
            {"type": "ГС", "plan": 22, "fact": 23}
          ]
          },
          {
            "period": "Февраль", "data": [
            {"type": "ННС", "plan": 24, "fact": 23},
            {"type": "ГС", "plan": 19, "fact": 23}
          ]
          },
          {
            "period": "Март", "data": [
            {"type": "ННС", "plan": 19, "fact": 23},
            {"type": "ГС", "plan": 18, "fact": 23}
          ]
          }
        ]
        },
        {
          "chartName": "Коэффициент тяжести аварий", "typeOfData": " ", "data": [
          {"period": "Январь", "LastYear": 20, "thisYear": 19},
          {"period": "Февраль", "LastYear": 23, "thisYear": 20},
          {"period": "Март", "LastYear": 19, "thisYear": 24},
          {"period": "Апрель", "LastYear": 19, "thisYear": 24},
          {"period": "Май", "LastYear": 19, "thisYear": 24}
        ]
        }
      ]
    }
  },
  {
    "year":    {
      "type": "eks", "data": [
        {"chartName": "НПВ", "typeOfData": " ", "data": [{"pv": 69, "npv": 31}]},
        {
          "chartName": "Скорость строительства скважин", "typeOfData": " ", "data": [
          {
            "period": "Январь", "data": [
            {"type": "ННС", "plan": 23, "fact": 21},
            {"type": "ГС", "plan": 32, "fact": 21}
          ]
          },
          {
            "period": "Февраль", "data": [
            {"type": "ННС", "plan": 24, "fact": 21},
            {"type": "ГС", "plan": 39, "fact": 21}
          ]
          },
          {
            "period": "Март", "data": [
            {"type": "ННС", "plan": 39, "fact": 21},
            {"type": "ГС", "plan": 18, "fact": 21}
          ]
          }
        ]
        },
        {
          "chartName": "Количество бригад бурения", "typeOfData": " ", "data": [
          {"period": "Январь", "plan": 20, "fact": 39},
          {"period": "Февраль", "plan": 21, "fact": 20},
          {"period": "Март", "plan": 39, "fact": 24}
        ]
        },
        {
          "chartName": "Количество бригад освоения", "typeOfData": " ", "data": [
          {"period": "Январь", "plan": 20, "fact": 39},
          {"period": "Февраль", "plan": 21, "fact": 20},
          {"period": "Март", "plan": 39, "fact": 24}
        ]
        },
        {
          "chartName": "Количество введенных скважин", "typeOfData": " ", "data": [
          {"period": "Январь", "plan": 20, "fact": 39},
          {"period": "Февраль", "plan": 21, "fact": 20},
          {"period": "Март", "plan": 39, "fact": 24}
        ]
        },
        {
          "chartName": "Количество скважин законченных строительством", "typeOfData": " ", "data": [
          {"period": "Январь", "plan": 20, "fact": 39},
          {"period": "Февраль", "plan": 21, "fact": 20},
          {"period": "Март", "plan": 39, "fact": 24}
        ]
        },
        {
          "chartName": "Количество скважин законченных бурением", "typeOfData": " ", "data": [
          {"period": "Январь", "plan": 20, "fact": 39},
          {"period": "Февраль", "plan": 21, "fact": 20},
          {"period": "Март", "plan": 39, "fact": 24}
        ]
        },
        {
          "chartName": "Коэффициент аварийности", "typeOfData": " ", "data": [
          {"period": "Январь", "LastYear": 20, "thisYear": 39},
          {"period": "Февраль", "LastYear": 21, "thisYear": 20},
          {"period": "Март", "LastYear": 39, "thisYear": 24},
          {"period": "Апрель", "LastYear": 39, "thisYear": 24},
          {"period": "Май", "LastYear": 39, "thisYear": 24}
        ]
        },
        {
          "chartName": "Продолжительность строительства скважин", "typeOfData": " ", "data": [
          {
            "period": "Январь", "data": [
            {"type": "ННС", "plan": 23, "fact": 21},
            {"type": "ГС", "plan": 32, "fact": 21}
          ]
          },
          {
            "period": "Февраль", "data": [
            {"type": "ННС", "plan": 24, "fact": 21},
            {"type": "ГС", "plan": 39, "fact": 21}
          ]
          },
          {
            "period": "Март", "data": [
            {"type": "ННС", "plan": 39, "fact": 21},
            {"type": "ГС", "plan": 18, "fact": 21}
          ]
          }
        ]
        },
        {
          "chartName": "Продолжительность бурения скважин", "typeOfData": " ", "data": [
          {
            "period": "Январь", "data": [
            {"type": "ННС", "plan": 23, "fact": 21},
            {"type": "ГС", "plan": 32, "fact": 21}
          ]
          },
          {
            "period": "Февраль", "data": [
            {"type": "ННС", "plan": 24, "fact": 21},
            {"type": "ГС", "plan": 39, "fact": 21}
          ]
          },
          {
            "period": "Март", "data": [
            {"type": "ННС", "plan": 39, "fact": 21},
            {"type": "ГС", "plan": 18, "fact": 21}
          ]
          }
        ]
        },
        {
          "chartName": "Продолжительность освоения скважин", "typeOfData": " ", "data": [
          {
            "period": "Январь", "data": [
            {"type": "ННС", "plan": 23, "fact": 21},
            {"type": "ГС", "plan": 32, "fact": 21}
          ]
          },
          {
            "period": "Февраль", "data": [
            {"type": "ННС", "plan": 24, "fact": 21},
            {"type": "ГС", "plan": 39, "fact": 21}
          ]
          },
          {
            "period": "Март", "data": [
            {"type": "ННС", "plan": 39, "fact": 21},
            {"type": "ГС", "plan": 18, "fact": 21}
          ]
          }
        ]
        },
        {
          "chartName": "Коэффициент тяжести аварий", "typeOfData": " ", "data": [
          {"period": "Январь", "LastYear": 20, "thisYear": 39},
          {"period": "Февраль", "LastYear": 21, "thisYear": 20},
          {"period": "Март", "LastYear": 39, "thisYear": 24},
          {"period": "Апрель", "LastYear": 39, "thisYear": 24},
          {"period": "Май", "LastYear": 39, "thisYear": 24}
        ]
        }
      ]
    },
    "quarter": {
      "type": "eks", "data": [
        {"chartName": "НПВ", "typeOfData": " ", "data": [{"pv": 65, "npv": 35}]},
        {
          "chartName": "Скорость строительства скважин", "typeOfData": " ", "data": [
          {
            "period": "Январь", "data": [
            {"type": "ННС", "plan": 23, "fact": 21},
            {"type": "ГС", "plan": 32, "fact": 21}
          ]
          },
          {
            "period": "Февраль", "data": [
            {"type": "ННС", "plan": 24, "fact": 21},
            {"type": "ГС", "plan": 39, "fact": 21}
          ]
          },
          {
            "period": "Март", "data": [
            {"type": "ННС", "plan": 39, "fact": 21},
            {"type": "ГС", "plan": 18, "fact": 21}
          ]
          }
        ]
        },
        {
          "chartName": "Количество бригад бурения", "typeOfData": " ", "data": [
          {"period": "Январь", "plan": 20, "fact": 39},
          {"period": "Февраль", "plan": 21, "fact": 20},
          {"period": "Март", "plan": 39, "fact": 24}
        ]
        },
        {
          "chartName": "Количество бригад освоения", "typeOfData": " ", "data": [
          {"period": "Январь", "plan": 20, "fact": 39},
          {"period": "Февраль", "plan": 21, "fact": 20},
          {"period": "Март", "plan": 39, "fact": 24}
        ]
        },
        {
          "chartName": "Количество введенных скважин", "typeOfData": " ", "data": [
          {"period": "Январь", "plan": 20, "fact": 39},
          {"period": "Февраль", "plan": 21, "fact": 20},
          {"period": "Март", "plan": 39, "fact": 24}
        ]
        },
        {
          "chartName": "Количество скважин законченных строительством", "typeOfData": " ", "data": [
          {"period": "Январь", "plan": 20, "fact": 39},
          {"period": "Февраль", "plan": 21, "fact": 20},
          {"period": "Март", "plan": 39, "fact": 24}
        ]
        },
        {
          "chartName": "Количество скважин законченных бурением", "typeOfData": " ", "data": [
          {"period": "Январь", "plan": 20, "fact": 39},
          {"period": "Февраль", "plan": 21, "fact": 20},
          {"period": "Март", "plan": 39, "fact": 24}
        ]
        },
        {
          "chartName": "Коэффициент аварийности", "typeOfData": " ", "data": [
          {"period": "Январь", "LastYear": 20, "thisYear": 39},
          {"period": "Февраль", "LastYear": 21, "thisYear": 20},
          {"period": "Март", "LastYear": 39, "thisYear": 24},
          {"period": "Апрель", "LastYear": 39, "thisYear": 24},
          {"period": "Май", "LastYear": 39, "thisYear": 24}
        ]
        },
        {
          "chartName": "Продолжительность строительства скважин", "typeOfData": " ", "data": [
          {
            "period": "Январь", "data": [
            {"type": "ННС", "plan": 23, "fact": 21},
            {"type": "ГС", "plan": 32, "fact": 21}
          ]
          },
          {
            "period": "Февраль", "data": [
            {"type": "ННС", "plan": 24, "fact": 21},
            {"type": "ГС", "plan": 39, "fact": 21}
          ]
          },
          {
            "period": "Март", "data": [
            {"type": "ННС", "plan": 39, "fact": 21},
            {"type": "ГС", "plan": 18, "fact": 21}
          ]
          }
        ]
        },
        {
          "chartName": "Продолжительность бурения скважин", "typeOfData": " ", "data": [
          {
            "period": "Январь", "data": [
            {"type": "ННС", "plan": 23, "fact": 21},
            {"type": "ГС", "plan": 32, "fact": 21}
          ]
          },
          {
            "period": "Февраль", "data": [
            {"type": "ННС", "plan": 24, "fact": 21},
            {"type": "ГС", "plan": 39, "fact": 21}
          ]
          },
          {
            "period": "Март", "data": [
            {"type": "ННС", "plan": 39, "fact": 21},
            {"type": "ГС", "plan": 18, "fact": 21}
          ]
          }
        ]
        },
        {
          "chartName": "Продолжительность освоения скважин", "typeOfData": " ", "data": [
          {
            "period": "Январь", "data": [
            {"type": "ННС", "plan": 23, "fact": 21},
            {"type": "ГС", "plan": 32, "fact": 21}
          ]
          },
          {
            "period": "Февраль", "data": [
            {"type": "ННС", "plan": 24, "fact": 21},
            {"type": "ГС", "plan": 39, "fact": 21}
          ]
          },
          {
            "period": "Март", "data": [
            {"type": "ННС", "plan": 39, "fact": 21},
            {"type": "ГС", "plan": 18, "fact": 21}
          ]
          }
        ]
        },
        {
          "chartName": "Коэффициент тяжести аварий", "typeOfData": " ", "data": [
          {"period": "Январь", "LastYear": 20, "thisYear": 39},
          {"period": "Февраль", "LastYear": 21, "thisYear": 20},
          {"period": "Март", "LastYear": 39, "thisYear": 24},
          {"period": "Апрель", "LastYear": 39, "thisYear": 24},
          {"period": "Май", "LastYear": 39, "thisYear": 24}
        ]
        }
      ]
    },
    "month":   {
      "type": "eks", "data": [
        {"chartName": "НПВ", "typeOfData": " ", "data": [{"pv": 77, "npv": 23}]},
        {
          "chartName": "Скорость строительства скважин", "typeOfData": " ", "data": [
          {
            "period": "Январь", "data": [
            {"type": "ННС", "plan": 23, "fact": 21},
            {"type": "ГС", "plan": 32, "fact": 21}
          ]
          },
          {
            "period": "Февраль", "data": [
            {"type": "ННС", "plan": 24, "fact": 21},
            {"type": "ГС", "plan": 39, "fact": 21}
          ]
          },
          {
            "period": "Март", "data": [
            {"type": "ННС", "plan": 39, "fact": 21},
            {"type": "ГС", "plan": 18, "fact": 21}
          ]
          }
        ]
        },
        {
          "chartName": "Количество бригад бурения", "typeOfData": " ", "data": [
          {"period": "Январь", "plan": 20, "fact": 39},
          {"period": "Февраль", "plan": 21, "fact": 20},
          {"period": "Март", "plan": 39, "fact": 24}
        ]
        },
        {
          "chartName": "Количество бригад освоения", "typeOfData": " ", "data": [
          {"period": "Январь", "plan": 20, "fact": 39},
          {"period": "Февраль", "plan": 21, "fact": 20},
          {"period": "Март", "plan": 39, "fact": 24}
        ]
        },
        {
          "chartName": "Количество введенных скважин", "typeOfData": " ", "data": [
          {"period": "Январь", "plan": 20, "fact": 39},
          {"period": "Февраль", "plan": 21, "fact": 20},
          {"period": "Март", "plan": 39, "fact": 24}
        ]
        },
        {
          "chartName": "Количество скважин законченных строительством", "typeOfData": " ", "data": [
          {"period": "Январь", "plan": 20, "fact": 39},
          {"period": "Февраль", "plan": 21, "fact": 20},
          {"period": "Март", "plan": 39, "fact": 24}
        ]
        },
        {
          "chartName": "Количество скважин законченных бурением", "typeOfData": " ", "data": [
          {"period": "Январь", "plan": 20, "fact": 39},
          {"period": "Февраль", "plan": 21, "fact": 20},
          {"period": "Март", "plan": 39, "fact": 24}
        ]
        },
        {
          "chartName": "Коэффициент аварийности", "typeOfData": " ", "data": [
          {"period": "Январь", "LastYear": 20, "thisYear": 39},
          {"period": "Февраль", "LastYear": 21, "thisYear": 20},
          {"period": "Март", "LastYear": 39, "thisYear": 24},
          {"period": "Апрель", "LastYear": 39, "thisYear": 24},
          {"period": "Май", "LastYear": 39, "thisYear": 24}
        ]
        },
        {
          "chartName": "Продолжительность строительства скважин", "typeOfData": " ", "data": [
          {
            "period": "Январь", "data": [
            {"type": "ННС", "plan": 23, "fact": 21},
            {"type": "ГС", "plan": 32, "fact": 21}
          ]
          },
          {
            "period": "Февраль", "data": [
            {"type": "ННС", "plan": 24, "fact": 21},
            {"type": "ГС", "plan": 39, "fact": 21}
          ]
          },
          {
            "period": "Март", "data": [
            {"type": "ННС", "plan": 39, "fact": 21},
            {"type": "ГС", "plan": 18, "fact": 21}
          ]
          }
        ]
        },
        {
          "chartName": "Продолжительность бурения скважин", "typeOfData": " ", "data": [
          {
            "period": "Январь", "data": [
            {"type": "ННС", "plan": 23, "fact": 21},
            {"type": "ГС", "plan": 32, "fact": 21}
          ]
          },
          {
            "period": "Февраль", "data": [
            {"type": "ННС", "plan": 24, "fact": 21},
            {"type": "ГС", "plan": 39, "fact": 21}
          ]
          },
          {
            "period": "Март", "data": [
            {"type": "ННС", "plan": 39, "fact": 21},
            {"type": "ГС", "plan": 18, "fact": 21}
          ]
          }
        ]
        },
        {
          "chartName": "Продолжительность освоения скважин", "typeOfData": " ", "data": [
          {
            "period": "Январь", "data": [
            {"type": "ННС", "plan": 23, "fact": 21},
            {"type": "ГС", "plan": 32, "fact": 21}
          ]
          },
          {
            "period": "Февраль", "data": [
            {"type": "ННС", "plan": 24, "fact": 21},
            {"type": "ГС", "plan": 39, "fact": 21}
          ]
          },
          {
            "period": "Март", "data": [
            {"type": "ННС", "plan": 39, "fact": 21},
            {"type": "ГС", "plan": 18, "fact": 21}
          ]
          }
        ]
        },
        {
          "chartName": "Коэффициент тяжести аварий", "typeOfData": " ", "data": [
          {"period": "Январь", "LastYear": 20, "thisYear": 39},
          {"period": "Февраль", "LastYear": 21, "thisYear": 20},
          {"period": "Март", "LastYear": 39, "thisYear": 24},
          {"period": "Апрель", "LastYear": 39, "thisYear": 24},
          {"period": "Май", "LastYear": 39, "thisYear": 24}
        ]
        }
      ]
    }
  }
]
